{
  "_说明": "新增世界·第四批（延续只收战斗/力量体系）。SCP基金会/勇者王/剑风传奇/家庭教师/斗罗漫画等库中已有已剔；层层恐惧/面容(纯walking-sim无战斗)/高智能方程式(赛车)/龙与虎(恋爱)已过滤。maxTier据阶位战力图鉴。",
  "worlds": [
    { "cat": "共创恐怖/新怪谈", "name": "后室（Backrooms）", "maxTier": 3 },
    { "cat": "共创恐怖/新怪谈", "name": "都市传说", "maxTier": 4 },
    { "cat": "共创恐怖/新怪谈", "name": "恐鬼症（Phasmophobia）", "maxTier": 2 },
    { "cat": "共创恐怖/新怪谈", "name": "致命公司（Lethal Company）", "maxTier": 2 },

    { "cat": "经典机甲", "name": "装甲骑兵", "maxTier": 5 },
    { "cat": "经典机甲", "name": "机动警察", "maxTier": 4 },
    { "cat": "经典机甲", "name": "苍蓝钢铁的琶音", "maxTier": 6 },
    { "cat": "经典机甲", "name": "战斗妖精雪风", "maxTier": 6 },
    { "cat": "经典机甲", "name": "太空堡垒（Robotech）", "maxTier": 7 },
    { "cat": "经典机甲", "name": "魔神Z", "maxTier": 7 },
    { "cat": "经典机甲", "name": "盖塔机器人", "maxTier": 8 },
    { "cat": "经典机甲", "name": "银河机攻队", "maxTier": 6 },
    { "cat": "经典机甲", "name": "巨神战击队", "maxTier": 5 },
    { "cat": "经典机甲", "name": "铁甲小宝", "maxTier": 3 },
    { "cat": "经典机甲", "name": "恐龙特急克塞号", "maxTier": 6 },

    { "cat": "类魂/动作游戏", "name": "忍者龙剑传", "maxTier": 5 },
    { "cat": "类魂/动作游戏", "name": "黑神话：悟空", "maxTier": 7 },
    { "cat": "类魂/动作游戏", "name": "卧龙：苍天陨落", "maxTier": 5 },
    { "cat": "类魂/动作游戏", "name": "匹诺曹的谎言", "maxTier": 4 },
    { "cat": "类魂/动作游戏", "name": "噬血代码", "maxTier": 5 },
    { "cat": "类魂/动作游戏", "name": "对马岛之魂", "maxTier": 3 },
    { "cat": "类魂/动作游戏", "name": "恶魔城（Castlevania）", "maxTier": 6 },
    { "cat": "类魂/动作游戏", "name": "洛克人（Mega Man）", "maxTier": 6 },
    { "cat": "类魂/动作游戏", "name": "光明记忆", "maxTier": 3 },
    { "cat": "类魂/动作游戏", "name": "帕斯卡契约", "maxTier": 4 },
    { "cat": "类魂/动作游戏", "name": "影子武士（Shadow Warrior）", "maxTier": 4 },
    { "cat": "类魂/动作游戏", "name": "忍者之印", "maxTier": 4 },
    { "cat": "类魂/动作游戏", "name": "师父（Sifu）", "maxTier": 3 },

    { "cat": "战斗日轻/漫画", "name": "刀语", "maxTier": 4 },
    { "cat": "战斗日轻/漫画", "name": "空之境界（型月）", "maxTier": 5 },
    { "cat": "战斗日轻/漫画", "name": "落第骑士英雄谭", "maxTier": 5 },
    { "cat": "战斗日轻/漫画", "name": "学战都市", "maxTier": 5 },
    { "cat": "战斗日轻/漫画", "name": "双星之阴阳师", "maxTier": 5 },
    { "cat": "战斗日轻/漫画", "name": "青之驱魔师", "maxTier": 6 },
    { "cat": "战斗日轻/漫画", "name": "结界师", "maxTier": 5 },
    { "cat": "战斗日轻/漫画", "name": "传说的勇者的传说", "maxTier": 6 },
    { "cat": "战斗日轻/漫画", "name": "天镜的极北之星", "maxTier": 3 },
    { "cat": "战斗日轻/漫画", "name": "魔法战争", "maxTier": 4 },
    { "cat": "战斗日轻/漫画", "name": "灼眼的夏娜", "maxTier": 6 },
    { "cat": "战斗日轻/漫画", "name": "约会大作战", "maxTier": 5 },

    { "cat": "战斗韩漫/韩网文", "name": "绝世武神", "maxTier": 6 },
    { "cat": "战斗韩漫/韩网文", "name": "拔剑", "maxTier": 5 },
    { "cat": "战斗韩漫/韩网文", "name": "死灵法师", "maxTier": 6 },
    { "cat": "战斗韩漫/韩网文", "name": "通天之路", "maxTier": 6 },
    { "cat": "战斗韩漫/韩网文", "name": "逆天而行", "maxTier": 6 },
    { "cat": "战斗韩漫/韩网文", "name": "神级血脉", "maxTier": 6 },
    { "cat": "战斗韩漫/韩网文", "name": "最强出租车", "maxTier": 5 },
    { "cat": "战斗韩漫/韩网文", "name": "超能立方", "maxTier": 5 },
    { "cat": "战斗韩漫/韩网文", "name": "狂徒", "maxTier": 5 },
    { "cat": "战斗韩漫/韩网文", "name": "格斗实况", "maxTier": 4 },

    { "cat": "亚洲动作片", "name": "巴霍巴利王", "maxTier": 3 },
    { "cat": "亚洲动作片", "name": "RRR", "maxTier": 3 },
    { "cat": "亚洲动作片", "name": "拳霸", "maxTier": 2 },
    { "cat": "亚洲动作片", "name": "冬荫功", "maxTier": 2 },
    { "cat": "亚洲动作片", "name": "突袭（The Raid）", "maxTier": 2 },
    { "cat": "亚洲动作片", "name": "这个杀手不太冷", "maxTier": 2 },
    { "cat": "亚洲动作片", "name": "飓风营救", "maxTier": 2 },
    { "cat": "亚洲动作片", "name": "极限特工", "maxTier": 2 },
    { "cat": "亚洲动作片", "name": "龙争虎斗（李小龙）", "maxTier": 2 },
    { "cat": "亚洲动作片", "name": "精武门（李小龙）", "maxTier": 2 },
    { "cat": "亚洲动作片", "name": "猛龙过江", "maxTier": 2 },
    { "cat": "亚洲动作片", "name": "死亡游戏", "maxTier": 2 },
    { "cat": "亚洲动作片", "name": "杀破狼", "maxTier": 2 },
    { "cat": "亚洲动作片", "name": "导火线", "maxTier": 2 },

    { "cat": "欧美超英漫画", "name": "地狱神探（康斯坦丁）", "maxTier": 5 },
    { "cat": "欧美超英漫画", "name": "传教士（Preacher）", "maxTier": 6 },
    { "cat": "欧美超英漫画", "name": "沼泽怪物", "maxTier": 6 },
    { "cat": "欧美超英漫画", "name": "神奇四侠", "maxTier": 7 },
    { "cat": "欧美超英漫画", "name": "银影侠", "maxTier": 8 },
    { "cat": "欧美超英漫画", "name": "绿灯军团", "maxTier": 8 },
    { "cat": "欧美超英漫画", "name": "沙赞（DC）", "maxTier": 7 },
    { "cat": "欧美超英漫画", "name": "黑亚当（DC）", "maxTier": 7 },
    { "cat": "欧美超英漫画", "name": "海王（DC）", "maxTier": 6 },
    { "cat": "欧美超英漫画", "name": "神奇女侠（DC）", "maxTier": 7 },
    { "cat": "欧美超英漫画", "name": "原子侠", "maxTier": 5 },

    { "cat": "国漫/漫画(战斗)", "name": "镖人", "maxTier": 3 },
    { "cat": "国漫/漫画(战斗)", "name": "火凤燎原", "maxTier": 3 },
    { "cat": "国漫/漫画(战斗)", "name": "中华英雄", "maxTier": 5 },
    { "cat": "国漫/漫画(战斗)", "name": "从前有座灵剑山", "maxTier": 6 },
    { "cat": "国漫/漫画(战斗)", "name": "尸兄（我叫白小飞）", "maxTier": 6 },
    { "cat": "国漫/漫画(战斗)", "name": "端脑", "maxTier": 4 },
    { "cat": "国漫/漫画(战斗)", "name": "凸变英雄", "maxTier": 5 },
    { "cat": "国漫/漫画(战斗)", "name": "风起苍岚", "maxTier": 6 },
    { "cat": "国漫/漫画(战斗)", "name": "灵剑尊", "maxTier": 8 },
    { "cat": "国漫/漫画(战斗)", "name": "武神主宰", "maxTier": 8 },

    { "cat": "恐怖/生存游戏", "name": "零红蝶（Fatal Frame）", "maxTier": 3 },
    { "cat": "恐怖/生存游戏", "name": "死魂曲（Siren）", "maxTier": 3 },
    { "cat": "恐怖/生存游戏", "name": "除夕", "maxTier": 2 },
    { "cat": "恐怖/生存游戏", "name": "纸人", "maxTier": 2 },

    { "cat": "战锤/桌游战斗", "name": "战锤40K：星际战士", "maxTier": 7, "peakBeyond": true },
    { "cat": "战锤/桌游战斗", "name": "战锤：西格玛时代", "maxTier": 8, "peakBeyond": true },
    { "cat": "战锤/桌游战斗", "name": "阿斯塔特（Astartes）", "maxTier": 7 }
  ]
}
