[
    {
        "Batch":  "批次51",
        "Name":  "高达Z",
        "Tiers":  "四"
    },
    {
        "Batch":  "批次51",
        "Name":  "光环 (Halo) - 致远星",
        "Tiers":  "三、七"
    },
    {
        "Batch":  "批次51",
        "Name":  "英雄 (Heroes)",
        "Tiers":  "四、五、六"
    },
    {
        "Batch":  "批次52",
        "Name":  "高达ZZ",
        "Tiers":  "四"
    },
    {
        "Batch":  "批次52",
        "Name":  "环太平洋2：雷霆再起",
        "Tiers":  "二、三"
    },
    {
        "Batch":  "批次52",
        "Name":  "龙珠",
        "Tiers":  "一、二、三、五、七、九"
    },
    {
        "Batch":  "批次52",
        "Name":  "龙珠系列",
        "Tiers":  "六、七、九"
    },
    {
        "Batch":  "批次52",
        "Name":  "逆袭的夏亚",
        "Tiers":  "一、二、三、四、五、六、七"
    },
    {
        "Batch":  "批次53",
        "Name":  "高达G",
        "Tiers":  "四"
    },
    {
        "Batch":  "批次53",
        "Name":  "高达V",
        "Tiers":  "四"
    },
    {
        "Batch":  "批次53",
        "Name":  "高达W",
        "Tiers":  "四"
    },
    {
        "Batch":  "批次53",
        "Name":  "高达X",
        "Tiers":  "四"
    },
    {
        "Batch":  "批次53",
        "Name":  "高达铁血",
        "Tiers":  "四"
    },
    {
        "Batch":  "批次54",
        "Name":  "Z高达",
        "Tiers":  "一、二、三、五、六、七"
    },
    {
        "Batch":  "批次54",
        "Name":  "高达水星的魔女",
        "Tiers":  "四"
    },
    {
        "Batch":  "批次54",
        "Name":  "机动战士高达0079",
        "Tiers":  "六"
    },
    {
        "Batch":  "批次54",
        "Name":  "邪恶力量美剧",
        "Tiers":  "三、七"
    },
    {
        "Batch":  "批次54",
        "Name":  "英雄（hero美剧）",
        "Tiers":  "三、七"
    },
    {
        "Batch":  "批次55",
        "Name":  "ZZ高达",
        "Tiers":  "一、二、三、六、七"
    },
    {
        "Batch":  "批次55",
        "Name":  "阿修罗之怒",
        "Tiers":  "一、二、三、四、五、六、七"
    },
    {
        "Batch":  "批次55",
        "Name":  "博人传",
        "Tiers":  "一、二、三、四、五、六、七"
    },
    {
        "Batch":  "批次55",
        "Name":  "灵笼",
        "Tiers":  "一、二、三、四、五、六、七"
    },
    {
        "Batch":  "批次55",
        "Name":  "瑞克和莫蒂",
        "Tiers":  "一、二、三、四、五、六、七"
    },
    {
        "Batch":  "批次56",
        "Name":  "∀高达",
        "Tiers":  "一、二、三、五、六、七"
    },
    {
        "Batch":  "批次56",
        "Name":  "X高达",
        "Tiers":  "一、二、三、五、六、七"
    },
    {
        "Batch":  "批次56",
        "Name":  "地狱男爵",
        "Tiers":  "一、二、三、四、五、六、七"
    },
    {
        "Batch":  "批次56",
        "Name":  "青之驱魔师",
        "Tiers":  "一、二、三、四、五、六、七"
    },
    {
        "Batch":  "批次56",
        "Name":  "英雄（美剧）",
        "Tiers":  "一、二"
    },
    {
        "Batch":  "批次57",
        "Name":  "JOJO的奇妙冒险：幻影之血",
        "Tiers":  "四"
    },
    {
        "Batch":  "批次57",
        "Name":  "超时空要塞",
        "Tiers":  "一、二、三、四、五、六、七"
    },
    {
        "Batch":  "批次57",
        "Name":  "革命机Valvrave",
        "Tiers":  "四、六"
    },
    {
        "Batch":  "批次57",
        "Name":  "机动战士高达系列",
        "Tiers":  "一、二"
    },
    {
        "Batch":  "批次57",
        "Name":  "夏目友人帐",
        "Tiers":  "一、二、三、四、五、六、七"
    },
    {
        "Batch":  "批次58",
        "Name":  "怪兽8号",
        "Tiers":  "一、二、三、四、五、六、七"
    },
    {
        "Batch":  "批次58",
        "Name":  "黑之契约者",
        "Tiers":  "一、二、三、四、五、六、七"
    },
    {
        "Batch":  "批次58",
        "Name":  "我有一座恐怖屋",
        "Tiers":  "一、二、三、四、五、六、七"
    },
    {
        "Batch":  "批次58",
        "Name":  "异兽迷城",
        "Tiers":  "一、二、三、四、五、六、七"
    },
    {
        "Batch":  "批次58",
        "Name":  "银河护卫队1",
        "Tiers":  "四"
    },
    {
        "Batch":  "批次59",
        "Name":  "哥布林杀手",
        "Tiers":  "一、二、三、四、五、六、七"
    },
    {
        "Batch":  "批次59",
        "Name":  "路人超能100",
        "Tiers":  "一、二、三、四、五、六、七"
    },
    {
        "Batch":  "批次59",
        "Name":  "全金属狂潮",
        "Tiers":  "一、二、三、四、五、六、七"
    },
    {
        "Batch":  "批次59",
        "Name":  "神奇宝贝",
        "Tiers":  "一、二、三、五、六、七"
    },
    {
        "Batch":  "批次59",
        "Name":  "物理魔法使马修",
        "Tiers":  "一、二、三、四、五、六、七"
    },
    {
        "Batch":  "批次60",
        "Name":  "阿基拉",
        "Tiers":  "一、二、三、四、五、六"
    },
    {
        "Batch":  "批次60",
        "Name":  "权力的游戏",
        "Tiers":  "一、二、三、四、五、六、七"
    },
    {
        "Batch":  "批次60",
        "Name":  "拳愿阿修罗",
        "Tiers":  "一、二、三、四、五、六、七"
    },
    {
        "Batch":  "批次60",
        "Name":  "刃牙",
        "Tiers":  "一、二、三、四、五、六、七"
    },
    {
        "Batch":  "批次60",
        "Name":  "罪恶王冠",
        "Tiers":  "一、二、三、四、五、六、七"
    },
    {
        "Batch":  "批次61",
        "Name":  "结界师",
        "Tiers":  "一、二、三、五、六、七"
    },
    {
        "Batch":  "批次61",
        "Name":  "全职法师",
        "Tiers":  "一、二、三、四、五、六、七"
    },
    {
        "Batch":  "批次61",
        "Name":  "仙剑奇侠传1",
        "Tiers":  "一、二、三、四、五、六、七"
    },
    {
        "Batch":  "批次61",
        "Name":  "仙剑奇侠传3",
        "Tiers":  "一、二、三、四、五、六、七"
    },
    {
        "Batch":  "批次61",
        "Name":  "葬送的芙莉莲",
        "Tiers":  "一、二、三、五、六、七"
    },
    {
        "Batch":  "批次62",
        "Name":  "JOJO的奇妙冒险",
        "Tiers":  "一、二、三、五、六、七"
    },
    {
        "Batch":  "批次62",
        "Name":  "神印王座",
        "Tiers":  "一、二、三、四、五、六、七"
    },
    {
        "Batch":  "批次62",
        "Name":  "守望者",
        "Tiers":  "一、二、三、四、五、六、七"
    },
    {
        "Batch":  "批次62",
        "Name":  "仙剑奇侠传4",
        "Tiers":  "一、二、三、四、五、六、七"
    },
    {
        "Batch":  "批次62",
        "Name":  "斩！赤红之瞳",
        "Tiers":  "一、二、三、五、六、七"
    },
    {
        "Batch":  "批次63",
        "Name":  "革命机valvarve",
        "Tiers":  "一、二、三、五、七"
    },
    {
        "Batch":  "批次63",
        "Name":  "合金装备1",
        "Tiers":  "一、二、三、四、五、六、七"
    },
    {
        "Batch":  "批次63",
        "Name":  "合金装备2",
        "Tiers":  "一、二、三、四、五、六、七"
    },
    {
        "Batch":  "批次63",
        "Name":  "合金装备3",
        "Tiers":  "一、二、三、四、五、六、七"
    },
    {
        "Batch":  "批次63",
        "Name":  "黑袍纠察队",
        "Tiers":  "一、二、三、四、五、六、七"
    },
    {
        "Batch":  "批次64",
        "Name":  "合金装备4",
        "Tiers":  "一、二、三、四、五、六、七"
    },
    {
        "Batch":  "批次64",
        "Name":  "合金装备5：幻痛",
        "Tiers":  "一、二、三、四、五、六、七"
    },
    {
        "Batch":  "批次64",
        "Name":  "合金装备崛起：复仇",
        "Tiers":  "一、二、三、四、五、六、七"
    },
    {
        "Batch":  "批次64",
        "Name":  "一人之下",
        "Tiers":  "一、二、三、四、五、六、七"
    },
    {
        "Batch":  "批次64",
        "Name":  "只狼",
        "Tiers":  "一、二、三、四、五、六、七"
    },
    {
        "Batch":  "批次65",
        "Name":  "地下城与勇士",
        "Tiers":  "一、二、三、四、五、六、七"
    },
    {
        "Batch":  "批次65",
        "Name":  "哥斯拉2：怪兽之王",
        "Tiers":  "一、二、三、四、五、六、七"
    },
    {
        "Batch":  "批次65",
        "Name":  "哥斯拉2014",
        "Tiers":  "四"
    },
    {
        "Batch":  "批次65",
        "Name":  "康斯坦丁",
        "Tiers":  "一、二、三、四、五、六、七"
    },
    {
        "Batch":  "批次65",
        "Name":  "泰坦陨落2",
        "Tiers":  "一、二、三、四、五、六、七"
    },
    {
        "Batch":  "批次66",
        "Name":  "阿基拉 (Akira)",
        "Tiers":  "四、七"
    },
    {
        "Batch":  "批次66",
        "Name":  "死亡笔记",
        "Tiers":  "一、二、三"
    },
    {
        "Batch":  "批次66",
        "Name":  "仙剑奇侠传2",
        "Tiers":  "一、二、三、四、五、六、七"
    },
    {
        "Batch":  "批次66",
        "Name":  "仙剑奇侠传系列",
        "Tiers":  "七"
    },
    {
        "Batch":  "批次66",
        "Name":  "银翼杀手2049",
        "Tiers":  "一、二、三"
    },
    {
        "Batch":  "批次67",
        "Name":  "仙剑奇侠传3外传",
        "Tiers":  "一、二、五、六"
    },
    {
        "Batch":  "批次67",
        "Name":  "仙剑奇侠传3外传：问情篇",
        "Tiers":  "三、四、七"
    },
    {
        "Batch":  "批次67",
        "Name":  "仙剑奇侠传5",
        "Tiers":  "一、二、三、四、五、六、七"
    },
    {
        "Batch":  "批次67",
        "Name":  "仙剑奇侠传5前传",
        "Tiers":  "一、二、三、四、五、六、七"
    },
    {
        "Batch":  "批次67",
        "Name":  "仙剑奇侠传6",
        "Tiers":  "一、二、三、四、五、六、七"
    },
    {
        "Batch":  "批次68",
        "Name":  "冰与火之歌",
        "Tiers":  "一、二、三、四、五、六、七"
    },
    {
        "Batch":  "批次68",
        "Name":  "合金装备：和平行者",
        "Tiers":  "一、二、三、四、五、六、七"
    },
    {
        "Batch":  "批次68",
        "Name":  "合金装备5：原爆点",
        "Tiers":  "一、二、三、四、五、六、七"
    },
    {
        "Batch":  "批次68",
        "Name":  "合金装备系列",
        "Tiers":  "七"
    },
    {
        "Batch":  "批次68",
        "Name":  "仙剑奇侠传7",
        "Tiers":  "一、二、三、四、五、六、七"
    },
    {
        "Batch":  "批次69",
        "Name":  "反叛的鲁路修",
        "Tiers":  "一、二、三、四、五、六、七"
    },
    {
        "Batch":  "批次69",
        "Name":  "鬼泣1",
        "Tiers":  "一、二、三、四、五、六、七"
    },
    {
        "Batch":  "批次69",
        "Name":  "某科学的超电磁炮",
        "Tiers":  "一、二、三、四、五、六、七"
    },
    {
        "Batch":  "批次69",
        "Name":  "普罗米修斯",
        "Tiers":  "一、二、三、四、五、六、七"
    },
    {
        "Batch":  "批次69",
        "Name":  "死亡空间",
        "Tiers":  "二、三、四、五、六、七"
    },
    {
        "Batch":  "批次70",
        "Name":  "Dead Space",
        "Tiers":  "一"
    },
    {
        "Batch":  "批次70",
        "Name":  "鬼泣2",
        "Tiers":  "一、二、三、四、五、六、七"
    },
    {
        "Batch":  "批次70",
        "Name":  "鬼泣3",
        "Tiers":  "一、二、三、四、五、六、七"
    },
    {
        "Batch":  "批次70",
        "Name":  "鬼泣4",
        "Tiers":  "一、二、三、四、五、六、七"
    },
    {
        "Batch":  "批次70",
        "Name":  "鬼泣系列",
        "Tiers":  "七"
    },
    {
        "Batch":  "批次71",
        "Name":  "恶魔人",
        "Tiers":  "一、二、三、四、五、六、七"
    },
    {
        "Batch":  "批次71",
        "Name":  "鬼泣5",
        "Tiers":  "一、二、三、四、五、六、七"
    },
    {
        "Batch":  "批次71",
        "Name":  "虐杀原形1",
        "Tiers":  "一、二、三、四、五、六"
    },
    {
        "Batch":  "批次71",
        "Name":  "虐杀原形2",
        "Tiers":  "一、二、三、四、五、六"
    },
    {
        "Batch":  "批次71",
        "Name":  "虐杀原形系列",
        "Tiers":  "七"
    },
    {
        "Batch":  "批次72",
        "Name":  "成龙历险记",
        "Tiers":  "一、二、三、四、五、六、七"
    },
    {
        "Batch":  "批次72",
        "Name":  "合金装备崛起系列",
        "Tiers":  "一"
    },
    {
        "Batch":  "批次72",
        "Name":  "惊悚乐园",
        "Tiers":  "一、二、三、四、五、六、七"
    },
    {
        "Batch":  "批次72",
        "Name":  "控制",
        "Tiers":  "一、二、三、四、五、六、七"
    },
    {
        "Batch":  "批次72",
        "Name":  "泰坦陨落1",
        "Tiers":  "一、二、三、四、五、六、七"
    },
    {
        "Batch":  "批次73",
        "Name":  "哥斯拉（2014）",
        "Tiers":  "一、二、三、四、五、六、七"
    },
    {
        "Batch":  "批次73",
        "Name":  "哥斯拉×金刚：新帝国",
        "Tiers":  "一、二、三、四、五、六、七"
    },
    {
        "Batch":  "批次73",
        "Name":  "哥斯拉大战金刚",
        "Tiers":  "一、二、三、四、五、六、七"
    },
    {
        "Batch":  "批次73",
        "Name":  "哥斯拉系列",
        "Tiers":  "二、七"
    },
    {
        "Batch":  "批次73",
        "Name":  "泰坦陨落系列",
        "Tiers":  "二、七"
    },
    {
        "Batch":  "批次74",
        "Name":  "火星异种",
        "Tiers":  "一、二、三、四、五、六、七"
    },
    {
        "Batch":  "批次74",
        "Name":  "强殖装甲凯普",
        "Tiers":  "一、二、三、四、五、六、七"
    },
    {
        "Batch":  "批次74",
        "Name":  "新·哥斯拉",
        "Tiers":  "一、二、三、四、五、六、七"
    },
    {
        "Batch":  "批次74",
        "Name":  "约会大作战",
        "Tiers":  "一、二、三、四、五、六、七"
    },
    {
        "Batch":  "批次74",
        "Name":  "再生侠",
        "Tiers":  "一、二、三、四、五、六、七"
    },
    {
        "Batch":  "批次75",
        "Name":  "钢铁侠1",
        "Tiers":  "一、二、三、四、五、六、七"
    },
    {
        "Batch":  "批次75",
        "Name":  "钢铁侠2",
        "Tiers":  "一、二、三、四、五、六、七"
    },
    {
        "Batch":  "批次75",
        "Name":  "钢铁侠3",
        "Tiers":  "一、二、三、四、五、六、七"
    },
    {
        "Batch":  "批次75",
        "Name":  "关于我转生变成史莱姆这档事",
        "Tiers":  "一、二、三、四、五、六、七"
    },
    {
        "Batch":  "批次75",
        "Name":  "镇魂街",
        "Tiers":  "一、二、三、四、五、六、七"
    },
    {
        "Batch":  "批次76",
        "Name":  "DARLING in the FRANXX",
        "Tiers":  "一、二、三、四、五、六、七"
    },
    {
        "Batch":  "批次76",
        "Name":  "阿基拉 Akira",
        "Tiers":  "二、三、四、五、六、七"
    },
    {
        "Batch":  "批次76",
        "Name":  "碧蓝航线",
        "Tiers":  "一、二、三、四、五、六、七"
    },
    {
        "Batch":  "批次76",
        "Name":  "地球防卫少年",
        "Tiers":  "一、二、三、四、五、六、七"
    },
    {
        "Batch":  "批次76",
        "Name":  "钢铁侠系列",
        "Tiers":  "七"
    },
    {
        "Batch":  "批次77",
        "Name":  "耻辱1",
        "Tiers":  "一、二、三、四、五、六、七"
    },
    {
        "Batch":  "批次77",
        "Name":  "耻辱2",
        "Tiers":  "一、二、三、四、五、六、七"
    },
    {
        "Batch":  "批次77",
        "Name":  "盾之勇者成名录",
        "Tiers":  "一、二、三、四、五、六、七"
    },
    {
        "Batch":  "批次77",
        "Name":  "反叛的鲁鲁修",
        "Tiers":  "一、二、三、四、五、六、七"
    },
    {
        "Batch":  "批次77",
        "Name":  "无限斯特拉托斯",
        "Tiers":  "一、二、三、四、五、六、七"
    },
    {
        "Batch":  "批次78",
        "Name":  "耻辱：界外魔之死",
        "Tiers":  "一、二、三、四、五、六、七"
    },
    {
        "Batch":  "批次78",
        "Name":  "耻辱系列",
        "Tiers":  "七"
    },
    {
        "Batch":  "批次78",
        "Name":  "终结者1",
        "Tiers":  "一、二、三、四、五、六、七"
    },
    {
        "Batch":  "批次78",
        "Name":  "终结者2",
        "Tiers":  "一、二、三、四、五、六、七"
    },
    {
        "Batch":  "批次78",
        "Name":  "终结者3",
        "Tiers":  "一、二、三、四、五、六、七"
    },
    {
        "Batch":  "批次79",
        "Name":  "秦时明月",
        "Tiers":  "一、二、三、四、五、六、七"
    },
    {
        "Batch":  "批次79",
        "Name":  "终结者4：救世军",
        "Tiers":  "一、二、三、四、五、六、七"
    },
    {
        "Batch":  "批次79",
        "Name":  "终结者5：创世纪",
        "Tiers":  "一、二、三、四、五、六、七"
    },
    {
        "Batch":  "批次79",
        "Name":  "终结者6：黑暗命运",
        "Tiers":  "一、二、三、四、五、六、七"
    },
    {
        "Batch":  "批次79",
        "Name":  "终结者系列",
        "Tiers":  "七"
    },
    {
        "Batch":  "批次80",
        "Name":  "超能失控",
        "Tiers":  "一、二、三、四、五、六、七"
    },
    {
        "Batch":  "批次80",
        "Name":  "恶灵骑士",
        "Tiers":  "一、二、三、四、五、六、七"
    },
    {
        "Batch":  "批次80",
        "Name":  "猎天使魔女",
        "Tiers":  "一、二、三、四、五、六、七"
    },
    {
        "Batch":  "批次80",
        "Name":  "蜘蛛侠1（雷米）",
        "Tiers":  "一、四、五、六、七"
    },
    {
        "Batch":  "批次80",
        "Name":  "蜘蛛侠2（雷米）",
        "Tiers":  "一、四、五、六、七"
    },
    {
        "Batch":  "批次81",
        "Name":  "超凡蜘蛛侠1",
        "Tiers":  "一、二、三、四、五、六、七"
    },
    {
        "Batch":  "批次81",
        "Name":  "超凡蜘蛛侠2",
        "Tiers":  "一、二、三、四、五、六、七"
    },
    {
        "Batch":  "批次81",
        "Name":  "金刚狼系列",
        "Tiers":  "七"
    },
    {
        "Batch":  "批次81",
        "Name":  "蜘蛛侠：英雄归来",
        "Tiers":  "一、二、三、四、五、六、七"
    },
    {
        "Batch":  "批次81",
        "Name":  "蜘蛛侠3（雷米）",
        "Tiers":  "一、四、五、六、七"
    },
    {
        "Batch":  "批次82",
        "Name":  "蝙蝠侠（1989）",
        "Tiers":  "一、四、五、六、七"
    },
    {
        "Batch":  "批次82",
        "Name":  "蝙蝠侠归来",
        "Tiers":  "一、四、五、六、七"
    },
    {
        "Batch":  "批次82",
        "Name":  "蜘蛛侠：英雄无归",
        "Tiers":  "一、二、三、四、五、六、七"
    },
    {
        "Batch":  "批次82",
        "Name":  "蜘蛛侠：英雄远征",
        "Tiers":  "一、二、三、四、五、六、七"
    },
    {
        "Batch":  "批次82",
        "Name":  "蜘蛛侠系列",
        "Tiers":  "七"
    },
    {
        "Batch":  "批次83",
        "Name":  "蝙蝠侠：黑暗骑士",
        "Tiers":  "一、二、三、四、五、六、七"
    },
    {
        "Batch":  "批次83",
        "Name":  "蝙蝠侠：黑暗骑士崛起",
        "Tiers":  "一、二、三、四、五、六、七"
    },
    {
        "Batch":  "批次83",
        "Name":  "蝙蝠侠：侠影之谜",
        "Tiers":  "一、二、四、五、六、七"
    },
    {
        "Batch":  "批次83",
        "Name":  "蝙蝠侠与罗宾",
        "Tiers":  "一、四、五、六、七"
    },
    {
        "Batch":  "批次83",
        "Name":  "永远的蝙蝠侠",
        "Tiers":  "一、四、五、六、七"
    },
    {
        "Batch":  "批次84",
        "Name":  "蝙蝠侠系列",
        "Tiers":  "七"
    },
    {
        "Batch":  "批次84",
        "Name":  "生化危机1",
        "Tiers":  "一、二、三、四、五、六"
    },
    {
        "Batch":  "批次84",
        "Name":  "生化危机2",
        "Tiers":  "一、二、三、四、五、六"
    },
    {
        "Batch":  "批次84",
        "Name":  "生化危机3",
        "Tiers":  "一、二、三、四、五、六"
    },
    {
        "Batch":  "批次84",
        "Name":  "新蝙蝠侠",
        "Tiers":  "一、二、三、四、五、六、七"
    },
    {
        "Batch":  "批次85",
        "Name":  "生化危机4",
        "Tiers":  "一、二、三、四、五、六"
    },
    {
        "Batch":  "批次85",
        "Name":  "生化危机5",
        "Tiers":  "一、二、三、四、五、六"
    },
    {
        "Batch":  "批次85",
        "Name":  "生化危机6",
        "Tiers":  "一、二、三、四、五、六"
    },
    {
        "Batch":  "批次85",
        "Name":  "生化危机7",
        "Tiers":  "一、二、三、四、五、六"
    },
    {
        "Batch":  "批次85",
        "Name":  "生化危机8",
        "Tiers":  "一、二、三、四、五、六"
    },
    {
        "Batch":  "批次86",
        "Name":  "对魔忍",
        "Tiers":  "一、二、三、四、五、六、七"
    },
    {
        "Batch":  "批次86",
        "Name":  "法科高中的劣等生",
        "Tiers":  "四、五、六、七"
    },
    {
        "Batch":  "批次86",
        "Name":  "黑兽 (Kuroinu)",
        "Tiers":  "四、六"
    },
    {
        "Batch":  "批次86",
        "Name":  "黑兽",
        "Tiers":  "一、二、三、五、七"
    },
    {
        "Batch":  "批次86",
        "Name":  "监狱战舰",
        "Tiers":  "一、二、三、四、五、六、七"
    },
    {
        "Batch":  "批次87",
        "Name":  "浪客剑心",
        "Tiers":  "一、二、三、四"
    },
    {
        "Batch":  "批次87",
        "Name":  "魔都精兵的奴隶",
        "Tiers":  "一、二、三、四、五、六、七"
    },
    {
        "Batch":  "批次87",
        "Name":  "漆黑的子弹",
        "Tiers":  "一、二、三、四、五、六、七"
    },
    {
        "Batch":  "批次87",
        "Name":  "无头骑士异闻录",
        "Tiers":  "一、二、三、四、五、六、七"
    },
    {
        "Batch":  "批次87",
        "Name":  "异星觉醒",
        "Tiers":  "一、二、三、四、五、六、七"
    },
    {
        "Batch":  "批次88",
        "Name":  "暗黑地牢",
        "Tiers":  "一、二、三、四、五、六、七"
    },
    {
        "Batch":  "批次88",
        "Name":  "创：战纪",
        "Tiers":  "一、二、三、四、五、六、七"
    },
    {
        "Batch":  "批次88",
        "Name":  "风云",
        "Tiers":  "一、二、三、四、五、六、七"
    },
    {
        "Batch":  "批次88",
        "Name":  "明日边缘",
        "Tiers":  "一、二、三、四、五、六、七"
    },
    {
        "Batch":  "批次88",
        "Name":  "全职高手",
        "Tiers":  "一、二、三、四"
    },
    {
        "Batch":  "批次89",
        "Name":  "铳梦",
        "Tiers":  "一、二、三、四、五、六、七"
    },
    {
        "Batch":  "批次89",
        "Name":  "刀锋战士",
        "Tiers":  "一、二、三、四、五、六"
    },
    {
        "Batch":  "批次89",
        "Name":  "范海辛",
        "Tiers":  "一、二、三、四、五、六、七"
    },
    {
        "Batch":  "批次89",
        "Name":  "僵尸道长",
        "Tiers":  "一、二、三、四、五"
    },
    {
        "Batch":  "批次89",
        "Name":  "圣剑学院的魔剑使",
        "Tiers":  "一、二、三、四、五、六、七"
    },
    {
        "Batch":  "批次90",
        "Name":  "弗莱迪",
        "Tiers":  "二、三、四、五"
    },
    {
        "Batch":  "批次90",
        "Name":  "黑色星期五",
        "Tiers":  "一、二、三、四、五"
    },
    {
        "Batch":  "批次90",
        "Name":  "魔法科高中的劣等生",
        "Tiers":  "一、二、三"
    },
    {
        "Batch":  "批次90",
        "Name":  "学院默示录",
        "Tiers":  "四、六"
    },
    {
        "Batch":  "批次90",
        "Name":  "亚人",
        "Tiers":  "一、二、三、四、五、六"
    },
    {
        "Batch":  "批次91",
        "Name":  "Blade",
        "Tiers":  "七"
    },
    {
        "Batch":  "批次91",
        "Name":  "辐射4",
        "Tiers":  "一、二、三、四、五、六、七"
    },
    {
        "Batch":  "批次91",
        "Name":  "寂静岭",
        "Tiers":  "一、二、三、四、五、六"
    },
    {
        "Batch":  "批次91",
        "Name":  "僵尸世界大战",
        "Tiers":  "一、二、三、四、五、六"
    },
    {
        "Batch":  "批次91",
        "Name":  "求生之路2",
        "Tiers":  "一、二、三、四、五、六"
    },
    {
        "Batch":  "批次92",
        "Name":  "釜山行",
        "Tiers":  "一、二、三、四、五、六"
    },
    {
        "Batch":  "批次92",
        "Name":  "剑豪生死斗",
        "Tiers":  "一、二、三、四"
    },
    {
        "Batch":  "批次92",
        "Name":  "特种部队",
        "Tiers":  "七"
    },
    {
        "Batch":  "批次92",
        "Name":  "甜蜜家园",
        "Tiers":  "一、二、三、四、五、六"
    },
    {
        "Batch":  "批次92",
        "Name":  "细胞分裂",
        "Tiers":  "一、二、三、四、五、七"
    },
    {
        "Batch":  "批次93",
        "Name":  "Metro 2033",
        "Tiers":  "六"
    },
    {
        "Batch":  "批次93",
        "Name":  "大逃杀",
        "Tiers":  "一、二、三、四、五"
    },
    {
        "Batch":  "批次93",
        "Name":  "双城之战",
        "Tiers":  "一、二、三、四、五、六、七"
    },
    {
        "Batch":  "批次93",
        "Name":  "未来日记",
        "Tiers":  "一、二、三、四、五、六、七"
    },
    {
        "Batch":  "批次93",
        "Name":  "最后的生还者",
        "Tiers":  "一、二、三、四、六"
    },
    {
        "Batch":  "批次94",
        "Name":  "SCP基金会",
        "Tiers":  "一、二、三、六、七"
    },
    {
        "Batch":  "批次94",
        "Name":  "地铁2033",
        "Tiers":  "一、二、三、四、五"
    },
    {
        "Batch":  "批次94",
        "Name":  "军火女王",
        "Tiers":  "一、二、三、四"
    },
    {
        "Batch":  "批次94",
        "Name":  "神话版三国",
        "Tiers":  "四、五、六、七"
    },
    {
        "Batch":  "批次94",
        "Name":  "特种部队：眼镜蛇的崛起",
        "Tiers":  "一、二、三、四、五、六"
    },
    {
        "Batch":  "批次95",
        "Name":  "寄生前夜",
        "Tiers":  "一、二、三、四、五、六、七"
    },
    {
        "Batch":  "批次95",
        "Name":  "甲铁城的卡巴内瑞",
        "Tiers":  "一、二、三、四、五、六、七"
    },
    {
        "Batch":  "批次95",
        "Name":  "林中小屋",
        "Tiers":  "一、二、三、四、五、六"
    },
    {
        "Batch":  "批次95",
        "Name":  "人类清除计划",
        "Tiers":  "一、二、三、四、六"
    },
    {
        "Batch":  "批次95",
        "Name":  "吸血鬼猎人D",
        "Tiers":  "一、二、三、四、五、六、七"
    },
    {
        "Batch":  "批次96",
        "Name":  "怪形",
        "Tiers":  "一、二、三、四、五、六"
    },
    {
        "Batch":  "批次96",
        "Name":  "甲贺忍法帖",
        "Tiers":  "一、二、三、四、五、六、七"
    },
    {
        "Batch":  "批次96",
        "Name":  "猛鬼街",
        "Tiers":  "一"
    },
    {
        "Batch":  "批次96",
        "Name":  "十二国记",
        "Tiers":  "一、二、三、四、五、六、七"
    },
    {
        "Batch":  "批次96",
        "Name":  "兽兵卫忍风帖",
        "Tiers":  "一、二、三、四、五、六、七"
    },
    {
        "Batch":  "批次97",
        "Name":  "SCP基金会·Site-19站点",
        "Tiers":  "四、五"
    },
    {
        "Batch":  "批次97",
        "Name":  "驱魔少年",
        "Tiers":  "一、二、三、四、五、六、七"
    },
    {
        "Batch":  "批次97",
        "Name":  "射雕英雄传",
        "Tiers":  "一、二、三、四"
    },
    {
        "Batch":  "批次97",
        "Name":  "行尸走肉",
        "Tiers":  "一、二、三、四、六"
    },
    {
        "Batch":  "批次97",
        "Name":  "移动迷宫",
        "Tiers":  "一、二、三、四"
    },
    {
        "Batch":  "批次98",
        "Name":  "寄生兽",
        "Tiers":  "一、二、三、四、五、六、七"
    },
    {
        "Batch":  "批次98",
        "Name":  "美国恐怖故事",
        "Tiers":  "六、七"
    },
    {
        "Batch":  "批次98",
        "Name":  "美国恐怖故事S1",
        "Tiers":  "一、二、三、四、五、七"
    },
    {
        "Batch":  "批次98",
        "Name":  "学园默示录",
        "Tiers":  "一、二、三"
    },
    {
        "Batch":  "批次98",
        "Name":  "炎拳",
        "Tiers":  "一、二、三、四、五、六、七"
    },
    {
        "Batch":  "批次99",
        "Name":  "美国恐怖故事S2",
        "Tiers":  "一、二、三、四、五、七"
    },
    {
        "Batch":  "批次99",
        "Name":  "美国恐怖故事S3",
        "Tiers":  "一、二、三、四、五、七"
    },
    {
        "Batch":  "批次99",
        "Name":  "美国恐怖故事S4",
        "Tiers":  "一、二、三、四、五、七"
    },
    {
        "Batch":  "批次99",
        "Name":  "美国恐怖故事S5",
        "Tiers":  "一、二、三、四、五、七"
    },
    {
        "Batch":  "批次99",
        "Name":  "美国恐怖故事S6",
        "Tiers":  "一、二、三、四、五、七"
    }
]
