[
  {
    "d": 857,
    "f": "同时穿越：继承万界遗产.md",
    "meta": "主库",
    "tiers": "一、二、三、四、五、六、七"
  },
  {
    "d": 857,
    "f": "宇智波赤石之旅.md",
    "meta": "主库",
    "tiers": "一、二、三、四、五、六"
  },
  {
    "d": 857,
    "f": "谁让他当假面骑士的！.md",
    "meta": "主库",
    "tiers": "一、二、三、四、五、六"
  },
  {
    "d": 857,
    "f": "贫民窟的游戏王.md",
    "meta": "主库",
    "tiers": "一、二、三、四、五"
  },
  {
    "d": 857,
    "f": "超人灭绝指南.md",
    "meta": "主库",
    "tiers": "一、二、三、四、五、六、七"
  },
  {
    "d": 858,
    "f": "呢喃诗章.md",
    "meta": "主库",
    "tiers": "一、二、三、四、五、六"
  },
  {
    "d": 858,
    "f": "天珠变.md",
    "meta": "主库",
    "tiers": "一、二、三、四、五、六、七、八"
  },
  {
    "d": 858,
    "f": "谁说我做的魔法卡牌有问题？.md",
    "meta": "主库",
    "tiers": "一、二、三、四、五、六"
  },
  {
    "d": 858,
    "f": "陈二狗的妖孽人生.md",
    "meta": "主库",
    "tiers": "一、二"
  },
  {
    "d": 858,
    "f": "魔王大人深不可测.md",
    "meta": "主库",
    "tiers": "一、二、三、四、五、六"
  },
  {
    "d": 859,
    "f": "古代末世的文弱书生.md",
    "meta": "主库",
    "tiers": "一、二、三、四、五、六"
  },
  {
    "d": 859,
    "f": "天人图谱.md",
    "meta": "主库",
    "tiers": "一、二、三、四、五、六、七、八"
  },
  {
    "d": 859,
    "f": "太尊！.md",
    "meta": "主库",
    "tiers": "一、二、三、四、五、六、七、八"
  },
  {
    "d": 859,
    "f": "我创造了怪物序列！.md",
    "meta": "主库",
    "tiers": "一、二、三、四、五、六"
  },
  {
    "d": 859,
    "f": "超级兵王.md",
    "meta": "主库",
    "tiers": "一、二"
  },
  {
    "d": 860,
    "f": "一世之尊.md",
    "meta": "主库",
    "tiers": "一、二、三、四、五、六、七、八"
  },
  {
    "d": 860,
    "f": "吞噬星空2：起源大陆.md",
    "meta": "主库",
    "tiers": "一、二、三、四、五、六、七、八"
  },
  {
    "d": 860,
    "f": "我都成超人了，灵气才复苏？.md",
    "meta": "主库",
    "tiers": "一、二、三、四、五、六、七"
  },
  {
    "d": 860,
    "f": "深海余烬.md",
    "meta": "主库",
    "tiers": "一、二、三、四、五、六、七"
  },
  {
    "d": 860,
    "f": "鸣龙.md",
    "meta": "主库",
    "tiers": "一、二、三、四、五、六、七"
  },
  {
    "d": 861,
    "f": "从武道世界开始击穿深渊.md",
    "meta": "主库",
    "tiers": "一、二、三、四、五、六、七"
  },
  {
    "d": 861,
    "f": "你这义体合法吗.md",
    "meta": "主库",
    "tiers": "一、二、三、四、五"
  },
  {
    "d": 861,
    "f": "异常生物见闻录.md",
    "meta": "主库",
    "tiers": "一、二、三、四、五、六、七"
  },
  {
    "d": 861,
    "f": "末世第一狠人.md",
    "meta": "主库",
    "tiers": "一、二、三、四、五"
  },
  {
    "d": 861,
    "f": "黄昏分界.md",
    "meta": "主库",
    "tiers": "一、二、三、四、五、六、七"
  },
  {
    "d": 862,
    "f": "噩梦使徒.md",
    "meta": "主库",
    "tiers": "一、二、三、四、五、六"
  },
  {
    "d": 862,
    "f": "我在神异司斩邪.md",
    "meta": "主库",
    "tiers": "一、二、三、四、五"
  },
  {
    "d": 862,
    "f": "玩家请上车.md",
    "meta": "主库",
    "tiers": "一、二、三、四、五"
  },
  {
    "d": 862,
    "f": "现实编程协会.md",
    "meta": "主库",
    "tiers": "一、二、三、四、五"
  },
  {
    "d": 862,
    "f": "谁说这里有怪谈的？.md",
    "meta": "主库",
    "tiers": "一、二、三、四、五"
  },
  {
    "d": 863,
    "f": "伪像报告.md",
    "meta": "主库",
    "tiers": "一、二、三、四、五"
  },
  {
    "d": 863,
    "f": "屠魔快刀.md",
    "meta": "主库",
    "tiers": "一、二、三、四、五"
  },
  {
    "d": 863,
    "f": "欢迎来到诡诞游戏.md",
    "meta": "主库",
    "tiers": "一、二、三、四、五"
  },
  {
    "d": 863,
    "f": "深渊片场.md",
    "meta": "主库",
    "tiers": "一、二、三、四、五、六"
  },
  {
    "d": 863,
    "f": "神秘复苏：假如.md",
    "meta": "主库",
    "tiers": "一、二、三、四、五、六"
  },
  {
    "d": 864,
    "f": "不死的我速通灵异游戏.md",
    "meta": "主库",
    "tiers": "一、二、三、四、五"
  },
  {
    "d": 864,
    "f": "出马大舞台，有仙你就来.md",
    "meta": "主库",
    "tiers": "一、二、三、四、五"
  },
  {
    "d": 864,
    "f": "天官赐邪.md",
    "meta": "主库",
    "tiers": "一、二、三、四、五"
  },
  {
    "d": 864,
    "f": "我的治愈系游戏.md",
    "meta": "主库",
    "tiers": "一、二、三、四、五"
  },
  {
    "d": 864,
    "f": "鬼上房.md",
    "meta": "主库",
    "tiers": "一、二、三、四"
  },
  {
    "d": 865,
    "f": "全球冰封：我打造了末日安全屋.md",
    "meta": "主库",
    "tiers": "一、二、三、四"
  },
  {
    "d": 865,
    "f": "废土.md",
    "meta": "主库",
    "tiers": "一、二、三、四、五"
  },
  {
    "d": 865,
    "f": "我的女友是丧尸.md",
    "meta": "主库",
    "tiers": "一、二、三、四、五"
  },
  {
    "d": 865,
    "f": "驱邪从食尸请神开始.md",
    "meta": "主库",
    "tiers": "一、二、三、四、五"
  },
  {
    "d": 865,
    "f": "黑暗血时代.md",
    "meta": "主库",
    "tiers": "一、二、三、四、五、六、七"
  },
  {
    "d": 866,
    "f": "亵渎.md",
    "meta": "主库",
    "tiers": "一、二、三、四、五、六、七、八"
  },
  {
    "d": 866,
    "f": "佣兵天下.md",
    "meta": "主库",
    "tiers": "一、二、三、四、五"
  },
  {
    "d": 866,
    "f": "末世之丧尸传奇.md",
    "meta": "主库",
    "tiers": "一、二、三、四、五"
  },
  {
    "d": 866,
    "f": "狩魔手记.md",
    "meta": "主库",
    "tiers": "一、二、三、四、五、六"
  },
  {
    "d": 866,
    "f": "紫川.md",
    "meta": "主库",
    "tiers": "一、二、三、四、五"
  },
  {
    "d": 867,
    "f": "光明纪元.md",
    "meta": "主库",
    "tiers": "一、二、三、四、五、六"
  },
  {
    "d": 867,
    "f": "大龙挂了.md",
    "meta": "主库",
    "tiers": "一、二、三、四、五"
  },
  {
    "d": 867,
    "f": "我的模拟长生路.md",
    "meta": "主库",
    "tiers": "一、二、三、四、五、六、七、八"
  },
  {
    "d": 867,
    "f": "谁让他修仙的！.md",
    "meta": "主库",
    "tiers": "一、二、三、四、五、六、七、八"
  },
  {
    "d": 867,
    "f": "魔法学徒.md",
    "meta": "主库",
    "tiers": "一、二、三、四、五、六"
  },
  {
    "d": 868,
    "f": "全球崩坏.md",
    "meta": "主库",
    "tiers": "一、二、三、四、五、六"
  },
  {
    "d": 868,
    "f": "大乘期才有逆袭系统.md",
    "meta": "主库",
    "tiers": "一、二、三、四、五、六、七、八"
  },
  {
    "d": 868,
    "f": "怪谈游戏设计师.md",
    "meta": "主库",
    "tiers": "一、二、三、四、五"
  },
  {
    "d": 868,
    "f": "活人深处.md",
    "meta": "主库",
    "tiers": "一、二、三、四、五"
  },
  {
    "d": 868,
    "f": "镇妖博物馆.md",
    "meta": "主库",
    "tiers": "一、二、三、四、五、六"
  },
  {
    "d": 869,
    "f": "噩梦惊袭.md",
    "meta": "主库",
    "tiers": "一、二、三、四、五、六"
  },
  {
    "d": 869,
    "f": "师妹，我真得控制你了.md",
    "meta": "主库",
    "tiers": "一、二、三、四、五、六、七"
  },
  {
    "d": 869,
    "f": "战锤：我也要坐黄金王座吗？.md",
    "meta": "主库",
    "tiers": "一、二、三、四、五、六、七"
  },
  {
    "d": 869,
    "f": "战锤：群星与蝼蚁.md",
    "meta": "主库",
    "tiers": "一、二、三、四、五、六、七"
  },
  {
    "d": 869,
    "f": "斗罗绝世：多情剑客无情剑.md",
    "meta": "主库",
    "tiers": "一、二、三、四、五、六、七"
  },
  {
    "d": 870,
    "f": "是，伟大魔女2077.md",
    "meta": "主库",
    "tiers": "一、二、三、四、五、六"
  }
]